setup.cfg
setup.py
cloverapi/__init__.py
cloverapi/cloverapi_auth.py
cloverapi/cloverapi_client.py
cloverapi/helpers/__init__.py
cloverapi/helpers/creator.py
cloverapi/services/__init__.py
cloverapi/services/app_service.py
cloverapi/services/cash_service.py
cloverapi/services/customer_service.py
cloverapi/services/employee_service.py
cloverapi/services/inventory_service.py
cloverapi/services/merchant_service.py
cloverapi/services/notification_service.py
cloverapi/services/order_service.py
cloverapi/services/payment_service.py
cloverapi_python.egg-info/PKG-INFO
cloverapi_python.egg-info/SOURCES.txt
cloverapi_python.egg-info/dependency_links.txt
cloverapi_python.egg-info/requires.txt
cloverapi_python.egg-info/top_level.txt
tests/__init__.py
tests/test_customer.py